apilookup/__init__.py
apilookup/_exceptions.py
apilookup-1.0.3.dist-info/METADATA
apilookup-1.0.3.dist-info/WHEEL
apilookup-1.0.3.dist-info/top_level.txt
apilookup-1.0.3.dist-info/RECORD
